{
    "name": "Северный заезд на дамбу",
    "n": {
        "walkable": true,
        "street": "Переулок Белый",
        "description": "Широкий переулок между административными зданиями с линией монорельса в центре."
    },
    "ne": {
        "street": "",
        "description": "Лестница к Набережной."
    },
    "e": {
        "street": "Улица Набережная",
        "description": "Широкая улица идущая под мостом по берегу реки с подвесной линией."
    },
    "se": {
        "street": "",
        "description": "Зона отдыха на берегу реки Глубоководной."
    },
    "s": {
        "walkable": true,
        "street": "Мост",
        "description": "Въезд на дамбу через реку Глубоководную."
    },
    "sw": {
        "street": "",
        "description": "Зона отдыха на берегу пруда."
    },
    "w": {
        "street": "Улица Набережная",
        "description": "Широкая улица идущая под мостом по берегу реки с подвесной линией."
    },
    "nw": {
        "street": "",
        "description": "Лестница к Набережной."
    },
    "description": ""
}