{
    "name": "Перекрёсток 625/125",
    "n": {
        "street": "Улица ???",
        "description": "Узкая тропа идущая через промзону."
    },
    "ne": {
        "street": "Промзона",
        "description": ""
    },
    "e": {
        "street": "Улица ???",
        "description": "Узкая тропа рабочего поселка."
    },
    "se": {
        "street": "",
        "description": "Низкоэтажная застройка рабочего поселка."
    },
    "s": {
        "street": "Улица ???",
        "description": "Узкая тропа рабочего поселка."
    },
    "sw": {
        "street": "",
        "description": "Низкоэтажная застройка рабочего поселка."
    },
    "w": {
        "street": "Улица ???",
        "description": "Узкая тропа рабочего поселка."
    },
    "nw": {
        "street": "Авиашкола",
        "description": ""
    },
    "description": ""
}